basepic.py
basepic-0.0.1.4.dist-info/WHEEL
basepic-0.0.1.4.dist-info/METADATA
basepic-0.0.1.4.dist-info/RECORD
