Metadata-Version: 2.1
Name: basepic
Version: 0.0.1.4
Summary: 超轻量级图片文件与base64的转换
Author-email: "Luo.yu_u-520" <luoyu_u@qq.com>
